lunar_calendar/__init__.py
lunar_calendar/constants.py
lunar_calendar/converters.py
lunar_calendar/julian_date_utils.py
lunar_calendar/lunar_calendar_core.py
lunar_calendar/perpetual_calendar.py
lunar_calendar/solar_terms.py
chinese_lunar_calendar_converter-0.1.0.dist-info/LICENSE
chinese_lunar_calendar_converter-0.1.0.dist-info/METADATA
chinese_lunar_calendar_converter-0.1.0.dist-info/WHEEL
chinese_lunar_calendar_converter-0.1.0.dist-info/top_level.txt
chinese_lunar_calendar_converter-0.1.0.dist-info/RECORD
