Metadata-Version: 2.1
Name: chinese_lunar_calendar_converter
Version: 0.1.0
Summary: A Python package for converting between Gregorian and Lunar calendars.
Home-page: https://github.com/ID-VerNe/lunar_calendar
Author: VerNe
Author-email: yuu_seeing@foxmail.com
Classifier: Programming Language :: Python :: 3
Classifier: License :: OSI Approved :: MIT License
Classifier: Operating System :: OS Independent
Classifier: Topic :: Scientific/Engineering :: Astronomy
Classifier: Topic :: Software Development :: Libraries :: Python Modules
Requires-Python: >=3.6
License-File: LICENSE
Requires-Dist: ephem
